{
  "type": "FeatureCollection",
  "features": [
    {
      "type": "Feature",
      "properties": { "name": "Biblioteca Nacional" },
      "geometry": { "type": "Point", "coordinates": [-3.692, 40.422] }
    },
    {
      "type": "Feature",
      "properties": { "name": "Biblioteca Municipal Centro" },
      "geometry": { "type": "Point", "coordinates": [-3.703, 40.417] }
    },
    {
      "type": "Feature",
      "properties": { "name": "Biblioteca Regional" },
      "geometry": { "type": "Point", "coordinates": [-3.675, 40.405] }
    }
  ]
}
